{
  "as_of": "2026-05-25",
  "generated_at": "2026-05-25 15:46:00 IST",
  "vix_latest": 19.63,
  "vix_regime": "ELEVATED \u2192 half size",
  "size_mult": 0.5,
  "n_candidates": 25,
  "picks": [
    {
      "rank": 1,
      "ticker": "ASTRAMICRO",
      "score": 10,
      "vol_mult": 5.3,
      "entry": 1235.6,
      "target": 1254.13,
      "shares": 53,
      "notional": 65487,
      "day_move_pct": 7.06,
      "notes": "30d+50d+period+vol>3x+trend+strong"
    },
    {
      "rank": 2,
      "ticker": "APOLLO",
      "score": 10,
      "vol_mult": 4.7,
      "entry": 408.2,
      "target": 414.32,
      "shares": 161,
      "notional": 65720,
      "day_move_pct": 14.44,
      "notes": "30d+50d+period+vol>3x+trend+strong"
    },
    {
      "rank": 3,
      "ticker": "BLISSGVS",
      "score": 9,
      "vol_mult": 5.1,
      "entry": 317.55,
      "target": 322.31,
      "shares": 207,
      "notional": 65733,
      "day_move_pct": 9.48,
      "notes": "30d+50d+period+vol>3x+trend"
    },
    {
      "rank": 4,
      "ticker": "TORNTPHARM",
      "score": 9,
      "vol_mult": 3.3,
      "entry": 4572.6,
      "target": 4641.19,
      "shares": 14,
      "notional": 64016,
      "day_move_pct": 3.24,
      "notes": "30d+50d+period+vol>3x+trend"
    },
    {
      "rank": 5,
      "ticker": "CARYSIL",
      "score": 9,
      "vol_mult": 3.1,
      "entry": 1116.55,
      "target": 1133.3,
      "shares": 59,
      "notional": 65876,
      "day_move_pct": 9.22,
      "notes": "30d+50d+period+vol>3x+trend"
    }
  ],
  "note": "Generated by manual chunked scan at 15:46 IST (cron failed earlier due to macOS FDA \u2014 fixed by 16:01 IST)."
}